python_fastapi_manager/__init__.py
python_fastapi_manager/__main__.py
python_fastapi_manager/apps/__init__.py
python_fastapi_manager/apps/registry.py
python_fastapi_manager/conf/__init__.py
python_fastapi_manager/conf/_global_settings.py
python_fastapi_manager/conf/global_settings.py
python_fastapi_manager/conf/templates/[app_name]/__init__.py-tpl
python_fastapi_manager/conf/templates/[app_name]/apps.py-tpl
python_fastapi_manager/conf/templates/[app_name]/migrations/__init__.py-tpl
python_fastapi_manager/conf/templates/[app_name]/models.py-tpl
python_fastapi_manager/conf/templates/[app_name]/repositories.py-tpl
python_fastapi_manager/conf/templates/[app_name]/routers.py-tpl
python_fastapi_manager/conf/templates/[app_name]/schemas.py-tpl
python_fastapi_manager/conf/templates/[app_name]/services.py-tpl
python_fastapi_manager/conf/templates/[project_name]/[project_name]/__init__.py-tpl
python_fastapi_manager/conf/templates/[project_name]/[project_name]/asgi.py-tpl
python_fastapi_manager/conf/templates/[project_name]/[project_name]/routers.py-tpl
python_fastapi_manager/conf/templates/[project_name]/[project_name]/settings.py-tpl
python_fastapi_manager/conf/templates/[project_name]/manage.py-tpl
python_fastapi_manager/core/app.py
python_fastapi_manager/core/managment/__init__.py
python_fastapi_manager/core/managment/cli.py
python_fastapi_manager/core/managment/handlers.py
python_fastapi_manager/db/__init__.py
python_fastapi_manager/db/base.py
python_fastapi_manager/db/connect.py
python_fastapi_manager/db/migrations/alembic/README
python_fastapi_manager/db/migrations/alembic/alembic.ini
python_fastapi_manager/db/migrations/alembic/env.py
python_fastapi_manager/db/migrations/alembic/script.py.mako
python_fastapi_manager/db/mixins.py
python_fastapi_manager/utils/__init__.py
python_fastapi_manager/utils/decorators.py
python_fastapi_manager/utils/functional.py
python_fastapi_manager-0.1.0.dist-info/METADATA
python_fastapi_manager-0.1.0.dist-info/WHEEL
python_fastapi_manager-0.1.0.dist-info/RECORD
